Workbook
Name AMORT: #REF!
Name ANNPMT: #REF!
Name BEDS: #REF!
Name CAP: #REF!
Name CITY: #REF!
Name COST: #REF!
Name EGI: #REF!
Name GI: #REF!
Name IPEGI: #REF!
Name IPNOI: #REF!
Name IPUCF: #REF!
Name K: #REF!
Name LEASINC: #REF!
Name loan: #REF!
Name LTV: #REF!
Name MAXLTV: #REF!
Name MOPMT: #REF!
Name name: #REF!
Name NOI: #REF!
Name nrsf: #REF!
Name OPEXP: #REF!
Name PARCEL: #REF!
Name PGI: #REF!
Name RATE: #REF!
Name STREET: #REF!
Name suites: #REF!
Name TERM: #REF!
Name UCF: #REF!
Name units: #REF!
Name VAC: #REF!
Name value: #REF!

Sheet Renovations
W2: Total Budget | Y2: per unit
W3: High End | X3: =SUM(W35,W72,Y99,Y110,Z123,Z152,AA189,AA230,AA243) -> 2173750 | Y3: =X3/37 -> 58750
W4: Low End | X4: =SUM(W36,W72,(Y99*0.75),(Y110*0.9),Z124,Z151,Z189,Z230,Z243) -> 1715112.5 | Y4: =X4/37 -> 46354.392
N5: =100000*37 -> 3700000
G7: =((500*12)*37)*0.55 -> 122100 | J7: You need roughly:
J9: $2,000,000 × 6.5% = $130,000 | W9: Phoenix contractors currently quote roughly $15,000-$25,000 for a kitchen refresh that retains the cabinet boxes and layout,
J11: of incremental annual NOI merely to create $2 million of additional property value.
W14: Scope | X14: What I would do | Y14: Rough cost/unit
W15: Demo/disposal | X15: Remove counters, appliances, fixtures, cabinet doors as needed | Y15: $500-$900
W16: Cabinets | X16: Keep existing boxes, repaint/reface with simple shaker-style doors, new hinges and pulls | Y16: $2,500-$4,000
W17: Quartz countertops | X17: Basic white/light quartz, standard edge | Y17: $2,000-$3,000
W18: Backsplash | X18: Simple subway tile or short quartz backsplash | Y18: $500-$900
W19: Sink + faucet | X19: Stainless undermount sink, modern pull-down faucet | Y19: $400-$700
W20: Refrigerator | X20: Basic stainless Energy Star model | Y20: $800-$1,100
W21: Dishwasher | X21: Basic stainless model | Y21: $450-$650
W22: Cooking appliances | X22: Cooktop + wall oven, or conventional range | Y22: $1,200-$2,000
W23: Hood/microwave | X23: Stainless vent hood or over-range microwave | Y23: $300-$550
W24: Lighting | X24: Remove fluorescent fixture; install modern LED flush mount/recessed lighting | Y24: $400-$800
W25: Electrical | X25: New outlets/switches/GFCI, minor appliance connections | Y25: $300-$700
... W29: Misc./GC/contingency | X29: Punch work, hardware, surprises | Y29: $1,200-$1,800
W30: Likely total | Y30: ~$13,000-$18,500
W35: =17500*37 -> 647500
W36: =13000*37 -> 481000
V48: Phoenix retail pricing for a cosmetic bath refresh is roughly $4,000-$8,000
W51: Item | X51: Recommended work | Y51: Underwriting cost/bath
W52: Demo/disposal | X52: Remove vanity, fixtures, mirror, toilet as needed | Y52: 350
W53: Vanity cabinet | X53: Basic shaker-style 30-36" vanity | Y53: 650
W54: Quartz top + sink | X54: Prefabricated quartz top with undermount sink | Y54: 500
W55: Sink faucet/plumbing | X55: Brushed-nickel faucet, drain, supply lines, install | Y55: 325
W56: Mirror | X56: Simple framed rectangular mirror | Y56: 175
W57: Vanity lighting | X57: Modern 2-3 light fixture, installed | Y57: 250
W58: Toilet | X58: New standard elongated toilet, installed | Y58: 400
W59: Tub refinishing | X59: Reglaze existing tub rather than replace | Y59: 550
W60: Tub surround | X60: Clean/regrout/recaulk existing white tile | Y60: 450
W61: Shower hardware | X61: New valve trim, tub spout and showerhead | Y61: 450
W62: Bathroom hardware | X62: Towel bar, TP holder, shower rod, hooks | Y62: 175
W64: Paint | X64: Walls, ceiling, trim and door | Y64: 350
... W66: Misc. plumbing/repairs | X66: Small unknown repairs behind fixtures | Y66: 350
W67: Direct cost | Y67: ~$5,825
W68: GC/contingency | X68: ~12%-15% | Y68: 800
W69: Underwriting total | Y69: =SUM(Y68,Y52:Y66) -> 6075
W72: =6075*63 -> 382725
W81: Line item | X81: Scope | Y81: 1BR 640 SF | Z81: 2BR 1,200 SF | AA81: 3BR 1,400 SF
W82: LVP flooring | X82: Midgrade commercial/durable LVP throughout | Y82: 3200 | Z82: 6000 | AA82: 7000
W83: Flooring demo/prep | X83: Remove old carpet/tile/LVP as needed, minor leveling | Y83: 600 | Z83: 900 | AA83: 1050
W84: Full interior paint | X84: Walls, ceilings, trim, doors | Y84: 2200 | Z84: 3000 | AA84: 3400
W85: Baseboards/trim | X85: Replace damaged/dated baseboard; caulk/paint | Y85: 600 | Z85: 900 | AA85: 1050
W86: Window coverings | X86: Replace vertical blinds with simple modern faux-wood blinds or roller shades | Y86: 700 | Z86: 1000 | AA86: 1150
W87: Interior door refresh | X87: Paint existing doors rather than replace wholesale | Y87: 300 | Z87: 450 | AA87: 500
W88: Door hardware | X88: Modern matching knobs/levers, hinges where needed | Y88: 300 | Z88: 450 | AA88: 500
W89: Lighting | X89: Modern flush mounts/ceiling fixtures, bedroom fixtures | Y89: 450 | Z89: 650 | AA89: 750
W90: Ceiling fans | X90: Living room + bedrooms where appropriate | Y90: 350 | Z90: 550 | AA90: 650
W91: Electrical finish | X91: New outlets, switches, cover plates, minor repairs | Y91: 300 | Z91: 450 | AA91: 500
W92: Closet hardware | X92: Rods/shelving/doors as needed | Y92: 250 | Z92: 350 | AA92: 400
W93: Smoke/CO detectors | X93: Replace/update as required | Y93: 100 | Z93: 150 | AA93: 175
W94: General punch/repairs | X94: Drywall, caulk, trim, miscellaneous | Y94: 500 | Z94: 700 | AA94: 800
W95: Total outside kitchen/bath | Y95: ~$9,850 | Z95: ~$15,550 | AA95: ~$18,000
W97: Laundry
W98: Laundry item | X98: Per-unit allowance | Y98: =9850*11 -> 108350 | Z98: =15550*24 -> 373200 | AA98: =18000*2 -> 36000
W99: Washer water supply + drain plumbing | X99: $800-$1,300 | Y99: =SUM(Y98:AA98) -> 517550
W100: Dryer electrical / 240V circuit | X100: $400-$700
W101: Dryer venting | X101: $400-$800
W102: Wall opening/repair | X102: $300-$500
W103: Closet/cabinet modification | X103: $600-$1,000
W104: Drain pan + shutoff/leak protection | X104: $150-$250
W105: Washer + dryer appliances | X105: $1,400-$1,800
W106: Delivery/installation | X106: $150-$250
W107: Permit/engineering allocation | X107: $150-$300
W108: Contingency | X108: $500-$800
W109: Total | X109: ~$4,850-$7,700/unit | Y109: =4850*40 -> 194000
Y110: =7700*40 -> 308000
V116: Line item | W116: Recommended work | X116: Est. cost/patio
V117: Pressure wash concrete | W117: Clean slab, walls and walkway | X117: $100-$175
V118: Concrete patch/seal | W118: Fill minor cracks/chips and seal where needed | X118: $100-$250
V119: Paint touch-up | W119: Posts, fascia, trim and adjacent exterior wall | X119: $150-$300
V120: Landscaping trim | W120: Cut back overgrowth/vines and clean planting edges | X120: $100-$200
V121: Gravel refresh | W121: Add/level matching decorative rock | X121: $75-$150
V122: Screen/slider service | W122: Repair rollers, screens, locks and weatherstripping as needed | X122: $100-$250
V123: Exterior light | W123: Simple modern patio fixture if one is absent/dated | X123: $125-$225 | Z123: =1675*37 -> 61975
V124: Misc. cleanup | W124: Debris removal, caulk, small hardware repairs | X124: $75-$125 | Z124: =825*37 -> 30525
V125: Typical total | X125: ~$825-$1,675
X138: w pool furniture | Y138: 8-10 commercial-grade loungers plus 3-4 dining/lounge tables and chairs | Z138: $5,000-$8,000
X139: Umbrellas + bases | Y139: 4-5 durable commercial umbrellas | Z139: $1,500-$2,500
X140: Pressure washing | Y140: Pool deck, coping, walls and surrounding hardscape | Z140: $750-$1,250
X141: Deck repairs | Y141: Patch cracks/chips and minor concrete repairs | Z141: $1,000-$2,500
X142: Pool handrail refresh | Y142: Clean/refinish or replace visibly dated rails | Z142: $500-$1,500
X143: Landscape cleanup | Y143: Trim vegetation, remove dead growth, reshape planting beds | Z143: $1,500-$3,000
X144: Landscape infill | Y144: Add a limited amount of drought-tolerant planting/rock where sparse | Z144: $1,000-$2,000
X145: Planter refresh | Y145: Clean/repair the blue-tile planter and replace struggling vegetation if needed | Z145: $500-$1,000
X146: Exterior lighting | Y146: Replace dated fixtures/add modest warm LED pathway/pool-area lighting | Z146: $1,500-$3,000
X147: Pool equipment allowance | Y147: Minor pump/filter/heater repairs discovered during diligence | Z147: $2,000-$4,000 reserve
X148: Signage/accessories | Y148: Updated rules signs, trash receptacles, small side tables | Z148: $500-$1,000
X149: Total cosmetic program | Z149: ~$15,000-$28,000
Z151: 15000
Z152: 28000
W177: Item | X177: Scope | Y177: Estimated property cost
W178: Pressure wash/prep | X178: Wash walls, soffits, stairs, railings and fascia before paint | Y178: $7,500-$12,000
W179: Exterior masonry/stucco paint | X179: Two-coat repaint of building walls | Y179: $40,000-$60,000
W180: Steel posts/railings/stairs | X180: Prep rust, prime and repaint charcoal/bronze | Y180: $10,000-$16,000
W181: Fascia/roof-edge paint | X181: Repaint visible fascia and trim | Y181: $6,000-$10,000
...

Sheet Summary
B2: The Hibiscus
B3: 5250 North 20th Street, Phoenix, AZ
B5: Property & Acquisition | D5: Investment Assumptions
B6: Year Built | C6: 1960 | D6: Renovation Costs | E6: ='Renovation Costs'!C21 -> 740000
B7: Units | C7: ='Unit Mix'!D7 -> 37 | D7: Reno Cost/Unit | E7: =E6/C7 -> 20000
B8: NRA (SF) | C8: ='Unit Mix'!F7 -> 38640 | D8: Reno Cost/SF | E8: =E6/C8 -> 19.151139
B9: Buildings | C9: 7 | D9: Closing Costs (%) | E9: 0.03
B10: Current Vacancy | C10: =1-91.8% -> 0.082 | D10: Stabilized Avg. Rent | E10: ='Unit Mix'!I7 -> 1355.5556
B11: Current Avg. Rent | C11: ='Unit Mix'!G7 -> 738.64865 | D11: Stabilized Vacancy | E11: =1-(35/37) -> 0.054054054
B12: Purchase Price | C12: =C7*75000 -> 2775000 | D12: Renovation Timeline | E12: 24 Months
B13: Price/Unit | C13: =C12/C7 -> 75000 | D13: Hold Period | E13: 3 Years
B14: Price/SF | C14: =C12/C8 -> 71.81677 | D14: Exit Cap | E14: ='Sale Comps'!J48+0.005 -> 0.065
B15: In-Place Operations | D15: Sources & Uses | F15: Returns | H15: Loan Assumptions
B16: Effective Gross Income | C16: ='Income Statements'!C8 -> 306008.08 | D16: Purchase Price | E16: =C12 -> 2775000 | F16: Sale Price | G16: ='Income Statements'!I31 -> 4871361 | H16: Loan Type | I16: Bridge - I/O
B17: Operating Expenses | C17: =-'Income Statements'!C22 -> -150300.4 | D17: Closing Costs | E17: =E16*E9 -> 83250 | F17: Exit Price/Unit | G17: =G16/C7 -> 131658.41 | H17: Amount | I17: =E22 -> 1942500
B18: Expense Ratio | C18: =ABS(C17/C16) -> 0.49116482 | D18: Renovation Costs | E18: ='Renovation Costs'!C21 -> 740000 | F18: Selling Costs | G18: =-G16*E9 -> -146140.83 | H18: Interest Reserve | I18: =E23 -> 296594.6
B19: NOI | C19: =C16+C17 -> 155707.68 | D19: Loan Closing Costs | E19: =E22*E9 -> 58275 | F19: Net Sale Proceeds | G19: =G16+G18 -> 4725220.2 | H19: Total Loan | I19: =SUM(I17:I18) -> 2239094.6
B20: Going-in Cap Rate | C20: =C19/C12 -> 0.056110874 | D20: Capitalized Interest | E20: ='Monthly DCF'!AM39-E22 -> 296594.6 | F20: All-in Basis/Unit | G20: =E21/C7 -> 106841.07 | H20: LTC | I20: =SUM(E22:E23)/E21 -> 0.56641206
B21: Stabilized Pro Forma | D21: Total Uses | E21: =SUM(E16:E20) -> 3953119.6 | F21: Development Spread | G21: =(C26-E14)*10000 -> 150.98378 | H21: Initial LTV | I21: 0.7
B22: Effective Gross Income | C22: ='Income Statements'!I8 -> 562777.33 | D22: Loan | E22: =E16*I21 -> 1942500 | F22: Unlevered IRR | G22: ='Monthly DCF'!C31 -> 0.17093083 | H22: Exit LTV | I22: =SUM(E22:E23)/G16 -> 0.45964456
B23: Operating Expenses | C23: =-'Income Statements'!I22 -> -246138.87 | D23: Interest Reserve | E23: =E20 -> 296594.6 | F23: Unlevered Equity Multiple | G23: ='Monthly DCF'!C32 -> 1.579728 | H23: Term | I23: 3 Years
B24: Expense Ratio | C24: =ABS(C23/C22) -> 0.43736457 | D24: Operating Cash Flow Retained | E24: {=_xlfn.LET(_xlpm.FCF,'Monthly DCF'!D20:AM20, _xlpm.Reno,ABS('Monthly DCF'!D25:AM25+'Monthly DCF'!D26:AM26), SUM(IF(_xlpm.FCF>0,IF(_xlpm.FCF<_xlpm.Reno,_xlpm.FCF,_xlpm.Reno),0)) )} -> 360675.55 | F24: Levered IRR | G24: ='Monthly DCF'!C44 -> 0.25481161 | H24: Rate | I24: 0.09
B25: NOI | C25: =C22+C23 -> 316638.47 | D25: Equity | E25: =E21-SUM(E22:E24) -> 1353349.5 | F25: Levered Equity Multiple | G25: ='Monthly DCF'!C45 -> 1.9152448 | H25: Stabilized DSCR | I25: ='Income Statements'!I29 -> 1.5712624
B26: Yield on Cost | C26: =C25/E21 -> 0.080098378 | D26: Total Sources | E26: =SUM(E22:E25) -> 3953119.6 | F26: Equity Requirement | G26: =E25 -> 1353349.5 | H26: Stabilized Debt Yield | I26: =C25/I19 -> 0.14141362
B27: Investment Thesis
B28: The Hibiscus is a 37-unit, 1960-vintage garden apartment community in Phoenix’s Biltmore area, where limited construction activity reduces direct competition from new supply. All units reportedly remain in classic condition, supporting a meaningful $20,000-per-unit interior and exterior renovation program. Direct rent comps support average stabilized rent of approximately $1,356 without relying on aggressive assumptions.
B32: Purchase Price Rationale
B33: Selected sale comps range from approximately $130,000 to $200,000 per unit but vary in condition and operating performance. A $2.775 million purchase price reflects the property’s low in-place NOI, capital needs and lease-up risk while limiting the all-in basis to approximately $106,800 per unit.
B36: Conclusion
B37: A purchase price of $2.775 million or lower represents the preferred basis. A higher price would require stronger support for achievable rents, lower renovation costs or a faster renovation schedule. Final pricing remains subject to verification of the rent roll, operating statements, contractor bids and deferred maintenance.

Sheet Unit Mix
B2: Unit Mix
B3: % of Units | C3: Type | D3: # of Units | E3: Unit SF | F3: Total SF | G3: In-Place Rent | H3: $/SF | I3: Stabilized Rent | J3: $/SF
B4: =D4/$D$7 -> 0.2972973 | C4: 1X1 | D4: 11 | E4: 640 | F4: =E4*D4 -> 7040 | G4: 630 | H4: =G4/E4 -> 0.984375 | I4: ='Rent Comps'!E43 -> 1162.4444 | J4: =I4/E4 -> 1.8163194
B5: =D5/$D$7 -> 0.64864865 | C5: 2X2 | D5: 24 | E5: 1200 | F5: =E5*D5 -> 28800 | G5: 750 | H5: =G5/E5 -> 0.625 | I5: ='Rent Comps'!E44 -> 1404.5 | J5: =I5/E5 -> 1.1704167
B6: =D6/$D$7 -> 0.054054054 | C6: 3X2 | D6: 2 | E6: 1400 | F6: =E6*D6 -> 2800 | G6: 1200 | H6: =G6/E6 -> 0.85714286 | I6: ='Rent Comps'!E45 -> 1830.3333 | J6: =I6/E6 -> 1.307381
B7: =SUM(B4:B6) -> 1 | D7: =SUM(D4:D6) -> 37 | E7: =F7/D7 -> 1044.3243 | F7: =SUM(F4:F6) -> 38640 | G7: =SUMPRODUCT(G4:G6,D4:D6)/D7 -> 738.64865 | H7: =G7/E7 -> 0.70729814 | I7: =SUMPRODUCT(I4:I6,D4:D6)/D7 -> 1355.5556 | J7: =I7/E7 -> 1.2980216
B9: Comments: | C9: In-place rents estimated based on stated in-place NOI while applying a roughly 50% operating expense ratio.

Sheet Income Statements
B2: In-Place Operations | C2: Annual | D2: Per Unit | E2: Per SF | F2: % of EGI | H2: Stabilized Pro Forma | I2: Annual | J2: Per Unit | K2: Per SF | L2: % of EGI
B3: Income | H3: Income
B4: Rental Income | C4: =SUM(('Unit Mix'!G4*'Unit Mix'!D4)+('Unit Mix'!G5*'Unit Mix'!D5)+('Unit Mix'!G6*'Unit Mix'!D6))*12 -> 327960 | D4: =C4/'Unit Mix'!$D$7 -> 8863.7838 | E4: =C4/'Unit Mix'!$F$7 -> 8.4875776 | F4: =C4/$C$8 -> 1.0717364 | H4: Rental Income | I4: =SUM(('Unit Mix'!I4*'Unit Mix'!D4)+('Unit Mix'!I5*'Unit Mix'!D5)+('Unit Mix'!I6*'Unit Mix'!D6))*12 -> 601866.67 | J4: =I4/'Unit Mix'!$D$7 -> 16266.667 | K4: =I4/'Unit Mix'!$F$7 -> 15.576259 | L4: =I4/$I$8 -> 1.0694579
B5: Less Vacancy | C5: =C4*(Summary!C10) -> 26892.72 | D5: =C5/'Unit Mix'!$D$7 -> 726.83027 | E5: =C5/'Unit Mix'!$F$7 -> 0.69598137 | F5: =C5/$C$8 -> 0.087882385 | H5: Less Vacancy | I5: =I4*(Summary!E11) -> 32533.333 | J5: =I5/'Unit Mix'!$D$7 -> 879.27928 | K5: =I5/'Unit Mix'!$F$7 -> 0.84195997 | L5: =I5/$I$8 -> 0.057808535
B6: Less Concessions/Bad Debt | C6: =C4*0.02 -> 6559.2 | D6: =C6/'Unit Mix'!$D$7 -> 177.27568 | E6: =C6/'Unit Mix'!$F$7 -> 0.16975155 | F6: =C6/$C$8 -> 0.021434728 | H6: Less Concessions/Bad Debt | I6: =I4*0.03 -> 18056 | J6: =I6/'Unit Mix'!$D$7 -> 488 | K6: =I6/'Unit Mix'!$F$7 -> 0.46728778 | L6: =I6/$I$8 -> 0.032083737
B7: Other Income | C7: 11500 | D7: =C7/'Unit Mix'!$D$7 -> 310.81081 | E7: =C7/'Unit Mix'!$F$7 -> 0.29761905 | F7: =C7/$C$8 -> 0.037580707 | H7: Other Income | I7: 11500 | J7: =I7/'Unit Mix'!$D$7 -> 310.81081 | K7: =I7/'Unit Mix'!$F$7 -> 0.29761905 | L7: =I7/$I$8 -> 0.02043437
B8: Effective Gross Income | C8: =C4-C5+C7-C6 -> 306008.08 | D8: =C8/'Unit Mix'!$D$7 -> 8270.4886 | E8: =C8/'Unit Mix'!$F$7 -> 7.9194638 | F8: =C8/$C$8 -> 1 | H8: Effective Gross Income | I8: =I4-I5+I7-I6 -> 562777.33 | J8: =I8/'Unit Mix'!$D$7 -> 15210.198 | K8: =I8/'Unit Mix'!$F$7 -> 14.564631 | L8: =I8/$I$8 -> 1
B10: Operating Expenses | H10: Operating Expenses
B11: Real Estate Taxes | C11: 35000 | D11: =C11/'Unit Mix'!$D$7 -> 945.94595 | E11: =C11/'Unit Mix'!$F$7 -> 0.9057971 | F11: =C11/$C$8 -> 0.11437606 | H11: Real Estate Taxes | I11: 38000 | J11: =I11/'Unit Mix'!$D$7 -> 1027.027 | K11: =I11/'Unit Mix'!$F$7 -> 0.98343685 | L11: =I11/$I$8 -> 0.067522265
B12: Property Insurance | C12: 18000 | D12: =C12/'Unit Mix'!$D$7 -> 486.48649 | E12: =C12/'Unit Mix'!$F$7 -> 0.46583851 | F12: =C12/$C$8 -> 0.058821976 | H12: Property Insurance | I12: 30000 | J12: =I12/'Unit Mix'!$D$7 -> 810.81081 | K12: =I12/'Unit Mix'!$F$7 -> 0.77639752 | L12: =I12/$I$8 -> 0.053307051
B13: Utilities | C13: 23000 | D13: =C13/'Unit Mix'!$D$7 -> 621.62162 | E13: =C13/'Unit Mix'!$F$7 -> 0.5952381 | F13: =C13/$C$8 -> 0.075161414 | H13: Utilities | I13: 40000 | J13: =I13/'Unit Mix'!$D$7 -> 1081.0811 | K13: =I13/'Unit Mix'!$F$7 -> 1.0351967 | L13: =I13/$I$8 -> 0.071076068
B14: Repairs & Maintenance | C14: 25000 | D14: =C14/'Unit Mix'!$D$7 -> 675.67568 | E14: =C14/'Unit Mix'!$F$7 -> 0.64699793 | F14: =C14/$C$8 -> 0.081697189 | H14: Repairs & Maintenance | I14: 40000 | J14: =I14/'Unit Mix'!$D$7 -> 1081.0811 | K14: =I14/'Unit Mix'!$F$7 -> 1.0351967 | L14: =I14/$I$8 -> 0.071076068
B15: Janitorial | C15: 3000 | D15: =C15/'Unit Mix'!$D$7 -> 81.081081 | E15: =C15/'Unit Mix'!$F$7 -> 0.077639752 | F15: =C15/$C$8 -> 0.0098036627 | H15: Janitorial | I15: 5000 | J15: =I15/'Unit Mix'!$D$7 -> 135.13514 | K15: =I15/'Unit Mix'!$F$7 -> 0.12939959 | L15: =I15/$I$8 -> 0.0088845085
B16: Management Fees | C16: =C8*0.05 -> 15300.404 | D16: =C16/'Unit Mix'!$D$7 -> 413.52443 | E16: =C16/'Unit Mix'!$F$7 -> 0.39597319 | F16: =C16/$C$8 -> 0.05 | H16: Management Fees | I16: =I8*0.05 -> 28138.867 | J16: =I16/'Unit Mix'!$D$7 -> 760.50991 | K16: =I16/'Unit Mix'!$F$7 -> 0.72823154 | L16: =I16/$I$8 -> 0.05
B17: Payroll & Benefits | C17: 15000 | D17: =C17/'Unit Mix'!$D$7 -> 405.40541 | E17: =C17/'Unit Mix'!$F$7 -> 0.38819876 | F17: =C17/$C$8 -> 0.049018314 | H17: Payroll & Benefits | I17: 32000 | J17: =I17/'Unit Mix'!$D$7 -> 864.86486 | K17: =I17/'Unit Mix'!$F$7 -> 0.82815735 | L17: =I17/$I$8 -> 0.056860854
B18: Advertising & Marketing | C18: 2500 | D18: =C18/'Unit Mix'!$D$7 -> 67.567568 | E18: =C18/'Unit Mix'!$F$7 -> 0.064699793 | F18: =C18/$C$8 -> 0.0081697189 | H18: Advertising & Marketing | I18: 5000 | J18: =I18/'Unit Mix'!$D$7 -> 135.13514 | K18: =I18/'Unit Mix'!$F$7 -> 0.12939959 | L18: =I18/$I$8 -> 0.0088845085
B19: Professional Fees | C19: 3000 | D19: =C19/'Unit Mix'!$D$7 -> 81.081081 | E19: =C19/'Unit Mix'!$F$7 -> 0.077639752 | F19: =C19/$C$8 -> 0.0098036627 | H19: Professional Fees | I19: 6000 | J19: =I19/'Unit Mix'!$D$7 -> 162.16216 | K19: =I19/'Unit Mix'!$F$7 -> 0.1552795 | L19: =I19/$I$8 -> 0.01066141
B20: General & Administrative | C20: 5500 | D20: =C20/'Unit Mix'!$D$7 -> 148.64865 | E20: =C20/'Unit Mix'!$F$7 -> 0.14233954 | F20: =C20/$C$8 -> 0.017973382 | H20: General & Administrative | I20: 12000 | J20: =I20/'Unit Mix'!$D$7 -> 324.32432 | K20: =I20/'Unit Mix'!$F$7 -> 0.31055901 | L20: =I20/$I$8 -> 0.02132282
B21: Other Expenses | C21: 5000 | D21: =C21/'Unit Mix'!$D$7 -> 135.13514 | E21: =C21/'Unit Mix'!$F$7 -> 0.12939959 | F21: =C21/$C$8 -> 0.016339438 | H21: Other Expenses | I21: 10000 | J21: =I21/'Unit Mix'!$D$7 -> 270.27027 | K21: =I21/'Unit Mix'!$F$7 -> 0.25879917 | L21: =I21/$I$8 -> 0.017769017
B22: Total Operating Expenses | C22: =SUM(C11:C21) -> 150300.4 | D22: =SUM(D11:D21) -> 4062.1731 | E22: =SUM(E11:E21) -> 3.889762 | F22: =C22/$C$8 -> 0.49116482 | H22: Total Operating Expenses | I22: =SUM(I11:I21) -> 246138.87 | J22: =SUM(J11:J21) -> 6652.4018 | K22: =SUM(K11:K21) -> 6.3700535 | L22: =I22/$I$8 -> 0.43736457
B24: Net Operating Income | C24: =C8-C22 -> 155707.68 | D24: =C24/'Unit Mix'!$D$7 -> 4208.3156 | E24: =C24/'Unit Mix'!$F$7 -> 4.0297018 | F24: =C24/$C$8 -> 0.50883518 | H24: Net Operating Income | I24: =I8-I22 -> 316638.47 | J24: =I24/'Unit Mix'!$D$7 -> 8557.7964 | K24: =I24/'Unit Mix'!$F$7 -> 8.1945773 | L24: =I24/$I$8 -> 0.56263543
B25: CapEx | C25: =D25*'Unit Mix'!D7 -> 9250 | D25: 250 | E25: =C25/'Unit Mix'!$F$7 -> 0.23938923 | F25: =C25/$C$8 -> 0.03022796 | H25: CapEx | I25: =J25*'Unit Mix'!D7 -> 9250 | J25: 250 | K25: =I25/'Unit Mix'!$F$7 -> 0.23938923 | L25: =I25/$I$8 -> 0.016436341
B26: Free Cash Flow | C26: =C24-C25 -> 146457.68 | D26: =C26/'Unit Mix'!$D$7 -> 3958.3156 | E26: =C26/'Unit Mix'!$F$7 -> 3.7903125 | F26: =C26/$C$8 -> 0.47860722 | H26: Free Cash Flow | I26: =I24-I25 -> 307388.47 | J26: =I26/'Unit Mix'!$D$7 -> 8307.7964 | K26: =I26/'Unit Mix'!$F$7 -> 7.9551881 | L26: =I26/$I$8 -> 0.54619909
H27: Financing Costs | I27: =SUM(Summary!E22:E23)*Summary!I24 -> 201518.51 | J27: =I27/'Unit Mix'!$D$7 -> 5446.4463 | K27: =I27/'Unit Mix'!$F$7 -> 5.2152825 | L27: =I27/$I$8 -> 0.35807859
B28: Comments: In-place income statement estimated based on marketed $156,000 NOI. | H28: Cash Flow after Debt Service | I28: =I26-I27 -> 105869.95 | J28: =I28/'Unit Mix'!$D$7 -> 2861.3501 | K28: =I28/'Unit Mix'!$F$7 -> 2.7399056 | L28: =I28/$I$8 -> 0.1881205
B29: Expenses estimated using average per unit costs in the market, and total expenses set to a conservative 50% operating expense ratio. | H29: DSCR | I29: =I24/I27 -> 1.5712624
H31: Value at Cap Rate of: | I31: =I24/H32 -> 4871361 | J31: =I31/'Unit Mix'!$D$7 -> 131658.41 | K31: =I31/'Unit Mix'!$F$7 -> 126.07042
H32: =Summary!E14 -> 0.065

Sheet Renovation Costs
B2: Renovation | C2: Cost | D2: Per Unit | E2: % of Budget | F2: Strategy
B3: Kitchen refreshes | C3: 185000 | D3: =C3/37 -> 5000 | E3: =C3/$C$21 -> 0.25 | F3: Paint/reface existing cabinets, new hardware, counters, sink/faucet, basic stainless appliances, modest lighting
B4: Bathroom refreshes | C4: 110000 | D4: =C4/37 -> 2972.973 | E4: =C4/$C$21 -> 0.14864865 | F4: Vanity/top, faucet, mirror, lighting, hardware, tub reglaze/regrout; avoid full gut renovation
B5: Flooring | C5: 78000 | D5: =C5/37 -> 2108.1081 | E5: =C5/$C$21 -> 0.10540541 | F5: LVP where needed; retain serviceable tile or flooring rather than replacing everything
B6: Full interior paint | C6: 52000 | D6: =C6/37 -> 1405.4054 | E6: =C6/$C$21 -> 0.07027027 | F6: Walls, ceilings and trim at turnover
B7: Lighting, electrical, hardware and blinds | C7: 42000 | D7: =C7/37 -> 1135.1351 | E7: =C7/$C$21 -> 0.056756757 | F7: Modern fixtures, switches/plates, door hardware and selective blinds
B8: Doors, trim, drywall and unit punch | C8: 25000 | D8: =C8/37 -> 675.67568 | E8: =C8/$C$21 -> 0.033783784 | F8: Repair and repaint rather than wholesale replacement
B9: Total Unit Interiors | C9: 492000 | D9: =C9/37 -> 13297.297 | E9: =C9/$C$21 -> 0.66486486
B10: Common laundry upgrade | C10: 20000 | D10: =C10/37 -> 540.54054 | E10: =C10/$C$21 -> 0.027027027 | F10: Refresh laundry room, add/replace machines and modern payment system
B11: Pool-area refresh | C11: 15000 | D11: =C11/37 -> 405.40541 | E11: =C11/$C$21 -> 0.02027027 | F11: Furniture, pressure washing, landscaping and minor repairs
B12: Exterior paint/stucco allowance | C12: 50000 | D12: =C12/37 -> 1351.3514 | E12: =C12/$C$21 -> 0.067567568 | F12: Targeted repainting and repairs rather than a complete premium repaint
B13: Landscaping/curb appeal | C13: 15000 | D13: =C13/37 -> 405.40541 | E13: =C13/$C$21 -> 0.02027027 | F13: Cleanup, gravel, selective planting and trimming
B14: Patio/balcony refresh | C14: 10000 | D14: =C14/37 -> 270.27027 | E14: =C14/$C$21 -> 0.013513514 | F14: Pressure wash, patch, touch-up and minor repairs
B15: Asphalt/striping | C15: 18000 | D15: =C15/37 -> 486.48649 | E15: =C15/$C$21 -> 0.024324324 | F15: Crack fill, sealcoat, patch and restripe
B16: Carport repairs/refresh | C16: 15000 | D16: =C16/37 -> 405.40541 | E16: =C16/$C$21 -> 0.02027027 | F16: Rust repair, paint and selective panel repairs
B17: Exterior lighting/signage | C17: 15000 | D17: =C17/37 -> 405.40541 | E17: =C17/$C$21 -> 0.02027027 | F17: New fixtures, numbers, signage and common-area presentation
B18: Deferred-maintenance reserve | C18: 35000 | D18: =C18/37 -> 945.94595 | E18: =C18/$C$21 -> 0.047297297 | F18: Plumbing, HVAC, electrical and miscellaneous discoveries
B19: GC/contingency | C19: 55000 | D19: =C19/37 -> 1486.4865 | E19: =C19/$C$21 -> 0.074324324 | F19: Approximately 7.4% of total budget
B20: Total Exterior Improvements | C20: =SUM(C10:C19) -> 248000 | D20: =C20/37 -> 6702.7027 | E20: =C20/$C$21 -> 0.33513514
B21: Total Renovation Costs | C21: =(C9)+SUM(C10:C19) -> 740000 | D21: =(D9)+SUM(D10:D19) -> 20000 | E21: =(E9)+SUM(E10:E19) -> 1
B23: Comments: The $20,000-per-unit budget supports a moderate value-add strategy focused on selective interior upgrades, targeted exterior improvements and deferred maintenance rather than heavy renovations.
B26: The property’s larger units and Biltmore location may also support in-unit laundry, particularly in two- and three-bedroom units, subject to plumbing, electrical and venting feasibility.
B30: Renovation Timeline
B31: Period | C31: Units Renovated | D31: Cumulative Units | E31: $ Amount | F31: Cumulative % Interior | G31: Exterior Upgrades | H31: Cumulative % Exterior
B32: Months 1-3 | C32: 4 | D32: 4 | E32: =C32*$D$9 -> 53189.189 | F32: {=SUM($E$32:E32/$C$9)} -> 0.10810811 | G32: =SUM(C10:C14) -> 110000 | H32: =SUM($G$32:G32)/SUM($C$10:$C$19) -> 0.44354839
B33: Months 4-6 | C33: 6 | D33: 10 | E33: =C33*$D$9 -> 79783.784 | F33: {=SUM($E$32:E33/$C$9)} -> 0.27027027 | G33: =SUM(C15:C19) -> 138000 | H33: =SUM($G$32:G33)/SUM($C$10:$C$19) -> 1
B34: Months 7-12 | C34: 10 | D34: 20 | E34: =C34*$D$9 -> 132972.97 | F34: {=SUM($E$32:E34/$C$9)} -> 0.54054054
B35: Months 13-18 | C35: 10 | D35: 30 | E35: =C35*$D$9 -> 132972.97 | F35: {=SUM($E$32:E35/$C$9)} -> 0.81081081
B36: Months 19-24 | C36: 7 | D36: 37 | E36: =C36*$D$9 -> 93081.081 | F36: {=SUM($E$32:E36/$C$9)} -> 1

Sheet Monthly DCF
A2: Cash Flow Projections | C2: 46387 | D2: 46418 | E2: =EOMONTH(D2,1) -> 46446 | F2: =EOMONTH(E2,1) -> 46477 | G2: =EOMONTH(F2,1) -> 46507 | H2: =EOMONTH(G2,1) -> 46538 | I2: =EOMONTH(H2,1) -> 46568 | J2: =EOMONTH(I2,1) -> 46599 | K2: =EOMONTH(J2,1) -> 46630 | L2: =EOMONTH(K2,1) -> 46660 | ... AM2: =EOMONTH(AL2,1) -> 47483
C3: 0 | D3: 1 | E3: =D3+1 -> 2 | F3: =E3+1 -> 3 | G3: =F3+1 -> 4 | H3: =G3+1 -> 5 | I3: =H3+1 -> 6 | J3: =I3+1 -> 7 | K3: =J3+1 -> 8 | L3: =K3+1 -> 9 | ... AM3: =AL3+1 -> 36
A4: Analysis Start Date | B4: Units renovated by month | D4: 1 | E4: 1 | F4: 2 | G4: 2 | H4: 2 | I4: 2 | J4: 2 | K4: 1 | L4: 2 | M4: 1 | N4: 2 | O4: 2 | P4: 1 | Q4: 1 | R4: 2 | S4: 2 | T4: 3 | U4: 1 | V4: 1 | W4: 2 | X4: 1 | Y4: 1 | Z4: 1 | AA4: 1
A5: 46387 | B5: Cumulative Renovated Units | D5: =SUM($D$4:D4) -> 1 | E5: =SUM($D$4:E4) -> 2 | F5: =SUM($D$4:F4) -> 4 | G5: =SUM($D$4:G4) -> 6 | H5: =SUM($D$4:H4) -> 8 | I5: =SUM($D$4:I4) -> 10 | J5: =SUM($D$4:J4) -> 12 | K5: =SUM($D$4:K4) -> 13 | ... AM5: =SUM($D$4:AM4) -> 37
A6: Renovation Timeline (Months) | B6: Renovated Units Online | D6: =SUM($C$4:C4) -> 0 | E6: =SUM($C$4:D4) -> 1 | F6: =SUM($C$4:E4) -> 2 | G6: =SUM($C$4:F4) -> 4 | H6: =SUM($C$4:G4) -> 6 | I6: =SUM($C$4:H4) -> 8 | J6: =SUM($C$4:I4) -> 10 | K6: =SUM($C$4:J4) -> 12 | ... AM6: =SUM($C$4:AL4) -> 37
A7: =Summary!E12 -> 24 Months | B7: Unrenovated Units Online | D7: ='Unit Mix'!$D$7-'Monthly DCF'!D4-'Monthly DCF'!D6 -> 36 | E7: ='Unit Mix'!$D$7-'Monthly DCF'!E4-'Monthly DCF'!E6 -> 35 | F7: ='Unit Mix'!$D$7-'Monthly DCF'!F4-'Monthly DCF'!F6 -> 33 | G7: ='Unit Mix'!$D$7-'Monthly DCF'!G4-'Monthly DCF'!G6 -> 31 | H7: ='Unit Mix'!$D$7-'Monthly DCF'!H4-'Monthly DCF'!H6 -> 29 | I7: ='Unit Mix'!$D$7-'Monthly DCF'!I4-'Monthly DCF'!I6 -> 27 | J7: ='Unit Mix'!$D$7-'Monthly DCF'!J4-'Monthly DCF'!J6 -> 25 | K7: ='Unit Mix'!$D$7-'Monthly DCF'!K4-'Monthly DCF'!K6 -> 24 | ... AM7: ='Unit Mix'!$D$7-'Monthly DCF'!AM4-'Monthly DCF'!AM6 -> 0
A8: Sale Date
A9: 47483
A10: Renovated Avg Rent | B10: Gross Rental Income | D10: =D7*('Unit Mix'!$G$7)+D6*($A$11) -> 26591.351 | E10: =E7*('Unit Mix'!$G$7)+E6*($A$11) -> 27208.258 | F10: =F7*('Unit Mix'!$G$7)+F6*($A$11) -> 27086.517 | G10: =G7*('Unit Mix'!$G$7)+G6*($A$11) -> 28320.33 | H10: =H7*('Unit Mix'!$G$7)+H6*($A$11) -> 29554.144 | I10: =I7*('Unit Mix'!$G$7)+I6*($A$11) -> 30787.958 | J10: =J7*('Unit Mix'!$G$7)+J6*($A$11) -> 32021.772 | K10: =K7*('Unit Mix'!$G$7)+K6*($A$11) -> 33994.234 | ... AM10: =AM7*('Unit Mix'!$G$7)+AM6*($A$11) -> 50155.556
A11: 1355.5556 | B11: Other Income | D11: ='Income Statements'!$I$7/12 -> 958.33333 | E11: ='Income Statements'!$I$7/12 -> 958.33333 | F11: ='Income Statements'!$I$7/12 -> 958.33333 | G11: ='Income Statements'!$I$7/12 -> 958.33333 | H11: ='Income Statements'!$I$7/12 -> 958.33333 | I11: ='Income Statements'!$I$7/12 -> 958.33333 | J11: ='Income Statements'!$I$7/12 -> 958.33333 | K11: ='Income Statements'!$I$7/12 -> 958.33333 | ... AM11: ='Income Statements'!$I$7/12 -> 958.33333
B12: Stabilized Vacancy | D12: =-(((D7*('Unit Mix'!$G$7))*Summary!$C$10)+((D6*('Unit Mix'!$I$7))*Summary!$E$11)) -> -2180.4908 | E12: =-(((E7*('Unit Mix'!$G$7))*Summary!$C$10)+((E6*('Unit Mix'!$I$7))*Summary!$E$11)) -> -2193.1949 | F12: =-(((F7*('Unit Mix'!$G$7))*Summary!$C$10)+((F6*('Unit Mix'!$I$7))*Summary!$E$11)) -> -2145.3298 | G12: =-(((G7*('Unit Mix'!$G$7))*Summary!$C$10)+((G6*('Unit Mix'!$I$7))*Summary!$E$11)) -> -2170.738 | H12: =-(((H7*('Unit Mix'!$G$7))*Summary!$C$10)+((H6*('Unit Mix'!$I$7))*Summary!$E$11)) -> -2196.1461 | I12: =-(((I7*('Unit Mix'!$G$7))*Summary!$C$10)+((I6*('Unit Mix'!$I$7))*Summary!$E$11)) -> -2221.5543 | J12: =-(((J7*('Unit Mix'!$G$7))*Summary!$C$10)+((J6*('Unit Mix'!$I$7))*Summary!$E$11)) -> -2246.9625 | K12: =-(((K7*('Unit Mix'!$G$7))*Summary!$C$10)+((K6*('Unit Mix'!$I$7))*Summary!$E$11)) -> -2332.9398 | ... AM12: =-(((AM7*('Unit Mix'!$G$7))*Summary!$C$10)+((AM6*('Unit Mix'!$I$7))*Summary!$E$11)) -> -2711.1111
B13: Concessions/Bad Debt | D13: =-(D7*('Income Statements'!$D$6/12))+-('Monthly DCF'!D6*('Income Statements'!$J$6/12)) -> -531.82703 | E13: =-(E7*('Income Statements'!$D$6/12))+-('Monthly DCF'!E6*('Income Statements'!$J$6/12)) -> -557.72072 | F13: =-(F7*('Income Statements'!$D$6/12))+-('Monthly DCF'!F6*('Income Statements'!$J$6/12)) -> -568.84144 | G13: =-(G7*('Income Statements'!$D$6/12))+-('Monthly DCF'!G6*('Income Statements'!$J$6/12)) -> -620.62883 | H13: =-(H7*('Income Statements'!$D$6/12))+-('Monthly DCF'!H6*('Income Statements'!$J$6/12)) -> -672.41622 | I13: =-(I7*('Income Statements'!$D$6/12))+-('Monthly DCF'!I6*('Income Statements'!$J$6/12)) -> -724.2036 | J13: =-(J7*('Income Statements'!$D$6/12))+-('Monthly DCF'!J6*('Income Statements'!$J$6/12)) -> -775.99099 | K13: =-(K7*('Income Statements'!$D$6/12))+-('Monthly DCF'!K6*('Income Statements'!$J$6/12)) -> -842.55135 | ... AM13: =-(AM7*('Income Statements'!$D$6/12))+-('Monthly DCF'!AM6*('Income Statements'!$J$6/12)) -> -1504.6667
B14: Effective Gross Income | D14: =SUM(D10:D13) -> 24837.367 | E14: =SUM(E10:E13) -> 25415.676 | F14: =SUM(F10:F13) -> 25330.679 | G14: =SUM(G10:G13) -> 26487.297 | H14: =SUM(H10:H13) -> 27643.915 | I14: =SUM(I10:I13) -> 28800.533 | J14: =SUM(J10:J13) -> 29957.152 | K14: =SUM(K10:K13) -> 31777.076 | ... AM14: =SUM(AM10:AM13) -> 46898.111
B16: Operating Expenses | D16: =-((D7*'Income Statements'!$D$22/12)+(D6*'Income Statements'!$J$22/12)) -> -12186.519 | E16: =-((E7*'Income Statements'!$D$22/12)+(E6*'Income Statements'!$J$22/12)) -> -12402.372 | F16: =-((F7*'Income Statements'!$D$22/12)+(F6*'Income Statements'!$J$22/12)) -> -12279.71 | G16: =-((G7*'Income Statements'!$D$22/12)+(G6*'Income Statements'!$J$22/12)) -> -12711.414 | H16: =-((H7*'Income Statements'!$D$22/12)+(H6*'Income Statements'!$J$22/12)) -> -13143.119 | I16: =-((I7*'Income Statements'!$D$22/12)+(I6*'Income Statements'!$J$22/12)) -> -13574.824 | J16: =-((J7*'Income Statements'!$D$22/12)+(J6*'Income Statements'!$J$22/12)) -> -14006.529 | K16: =-((K7*'Income Statements'!$D$22/12)+(K6*'Income Statements'!$J$22/12)) -> -14776.748 | ... AM16: =-((AM7*'Income Statements'!$D$22/12)+(AM6*'Income Statements'!$J$22/12)) -> -20511.572
B18: Net Operating Income | D18: =SUM(D14,D16) -> 12650.848 | E18: =SUM(E14,E16) -> 13013.304 | F18: =SUM(F14,F16) -> 13050.969 | G18: =SUM(G14,G16) -> 13775.882 | H18: =SUM(H14,H16) -> 14500.796 | I18: =SUM(I14,I16) -> 15225.709 | J18: =SUM(J14,J16) -> 15950.623 | K18: =SUM(K14,K16) -> 17000.328 | ... AM18: =SUM(AM14,AM16) -> 26386.539
B19: Capex | D19: =-'Income Statements'!$I$25/12 -> -770.83333 | E19: =-'Income Statements'!$I$25/12 -> -770.83333 | F19: =-'Income Statements'!$I$25/12 -> -770.83333 | G19: =-'Income Statements'!$I$25/12 -> -770.83333 | H19: =-'Income Statements'!$I$25/12 -> -770.83333 | I19: =-'Income Statements'!$I$25/12 -> -770.83333 | J19: =-'Income Statements'!$I$25/12 -> -770.83333 | K19: =-'Income Statements'!$I$25/12 -> -770.83333 | ... AM19: =-'Income Statements'!$I$25/12 -> -770.83333
B20: Free Cash Flow | D20: =D18+D19 -> 11880.014 | E20: =E18+E19 -> 12242.471 | F20: =F18+F19 -> 12280.136 | G20: =G18+G19 -> 13005.049 | H20: =H18+H19 -> 13729.963 | I20: =I18+I19 -> 14454.876 | J20: =J18+J19 -> 15179.79 | K20: =K18+K19 -> 16229.495 | ... AM20: =AM18+AM19 -> 25615.706
A21: Purchase Price
A22: =Summary!C12 -> 2775000 | B22: Purchase Price + Closing Costs | C22: =-((A22)+(A22*Summary!E9)) -> -2858250
A24: Reno Cost Factor | B24: Renovations
A25: 1 | B25: Interior Renovations | D25: =(-D4*'Renovation Costs'!$D$9)*$A$25 -> -13297.297 | E25: =(-E4*'Renovation Costs'!$D$9)*$A$25 -> -13297.297 | F25: =(-F4*'Renovation Costs'!$D$9)*$A$25 -> -26594.595 | G25: =(-G4*'Renovation Costs'!$D$9)*$A$25 -> -26594.595 | H25: =(-H4*'Renovation Costs'!$D$9)*$A$25 -> -26594.595 | I25: =(-I4*'Renovation Costs'!$D$9)*$A$25 -> -26594.595 | J25: =(-J4*'Renovation Costs'!$D$9)*$A$25 -> -26594.595 | K25: =(-K4*'Renovation Costs'!$D$9)*$A$25 -> -13297.297 | ... AM25: =(-AM4*'Renovation Costs'!$D$9)*$A$25 -> 0
B26: Exterior Renovations | D26: =(-'Renovation Costs'!$C$20/6)*$A$25 -> -41333.333 | E26: =(-'Renovation Costs'!$C$20/6)*$A$25 -> -41333.333 | F26: =(-'Renovation Costs'!$C$20/6)*$A$25 -> -41333.333 | G26: =(-'Renovation Costs'!$C$20/6)*$A$25 -> -41333.333 | H26: =(-'Renovation Costs'!$C$20/6)*$A$25 -> -41333.333 | I26: =(-'Renovation Costs'!$C$20/6)*$A$25 -> -41333.333
A27: Cap Rate
A28: 0.065 | B28: Reversion Value | C28: =IF(C2=$A$9,(C18*12/$A$28)*(1-Summary!$E$9),"0") -> 0 | D28: =IF(D2=$A$9,(D18*12/$A$28)*(1-Summary!$E$9),"0") -> 0 | E28: =IF(E2=$A$9,(E18*12/$A$28)*(1-Summary!$E$9),"0") -> 0 | F28: =IF(F2=$A$9,(F18*12/$A$28)*(1-Summary!$E$9),"0") -> 0 | G28: =IF(G2=$A$9,(G18*12/$A$28)*(1-Summary!$E$9),"0") -> 0 | H28: =IF(H2=$A$9,(H18*12/$A$28)*(1-Summary!$E$9),"0") -> 0 | I28: =IF(I2=$A$9,(I18*12/$A$28)*(1-Summary!$E$9),"0") -> 0 | J28: =IF(J2=$A$9,(J18*12/$A$28)*(1-Summary!$E$9),"0") -> 0 | ... AM28: =IF(AM2=$A$9,(AM18*12/$A$28)*(1-Summary!$E$9),"0") -> 4725220.2
B30: Unlevered Cash Flow | C30: =SUM(C25:C26,C22,C20,C28) -> -2858250 | D30: =SUM(D25:D26,D22,D20,D28) -> -42750.616 | E30: =SUM(E25:E26,E22,E20,E28) -> -42388.16 | F30: =SUM(F25:F26,F22,F20,F28) -> -55647.792 | G30: =SUM(G25:G26,G22,G20,G28) -> -54922.879 | H30: =SUM(H25:H26,H22,H20,H28) -> -54197.965 | I30: =SUM(I25:I26,I22,I20,I28) -> -53473.052 | J30: =SUM(J25:J26,J22,J20,J28) -> -11414.805 | ... AM30: =SUM(AM25:AM26,AM22,AM20,AM28) -> 4750835.9
B31: IRR | C31: =XIRR(C30:AM30,C2:AM2) -> 0.17093083
B32: Equity Multiple | C32: =SUMIF(C30:AM30,">0")/-SUMIF(C30:AM30,"<0") -> 1.579728
B34: Amount
A35: Senior Loan | B35: =Summary!E22 -> 1942500 | C35: =MIN($B$35,MAX(0,-C30)) -> 1942500 | D35: =MIN(MAX(0,D30),MAX(0,$B$35-SUM($C$35:C35))) -> 0 | E35: =MIN(MAX(0,E30),MAX(0,$B$35-SUM($C$35:D35))) -> 0 | F35: =MIN(MAX(0,F30),MAX(0,$B$35-SUM($C$35:E35))) -> 0 | G35: =MIN(MAX(0,G30),MAX(0,$B$35-SUM($C$35:F35))) -> 0 | H35: =MIN(MAX(0,H30),MAX(0,$B$35-SUM($C$35:G35))) -> 0 | I35: =MIN(MAX(0,I30),MAX(0,$B$35-SUM($C$35:H35))) -> 0 | J35: =MIN(MAX(0,J30),MAX(0,$B$35-SUM($C$35:I35))) -> 0 | K35: =MIN(MAX(0,K30),MAX(0,$B$35-SUM($C$35:J35))) -> 0 | ... AM35: =MIN(MAX(0,AM30),MAX(0,$B$35-SUM($C$35:AL35))) -> 0
A36: Loan Closing Costs | B36: =Summary!E22*0.03 -> 58275
A37: Equity Draw | B37: =SUM(C37:AM37) -> 1353349.5 | C37: =MIN(MAX(0,-C30-C35+B36)) -> 974025 | D37: =MIN(MAX(0,-D30-D35)) -> 42750.616 | E37: =MIN(MAX(0,-E30-E35)) -> 42388.16 | F37: =MIN(MAX(0,-F30-F35)) -> 55647.792 | G37: =MIN(MAX(0,-G30-G35)) -> 54922.879 | H37: =MIN(MAX(0,-H30-H35)) -> 54197.965 | I37: =MIN(MAX(0,-I30-I35)) -> 53473.052 | J37: =MIN(MAX(0,-J30-J35)) -> 11414.805 | K37: =MIN(MAX(0,-K30-K35)) -> 0 | ... AM37: =MIN(MAX(0,-AM30-AM35)) -> 0
A39: Financing Cost | B39: Loan Balance | C39: =C35 -> 1942500 | D39: =C39+C41 -> 1942500 | E39: =D39+D41 -> 1957068.7 | F39: =E39+E41 -> 1971746.8 | G39: =F39+F41 -> 1986534.9 | H39: =G39+G41 -> 2001433.9 | I39: =H39+H41 -> 2016444.6 | J39: =I39+I41 -> 2031568 | K39: =J39+J41 -> 2046804.7 | ... AM39: =AL39+AL41 -> 2239094.6
B40: Interest Expense | D40: =D39*(Summary!$I$24/12) -> 14568.75 | E40: =E39*(Summary!$I$24/12) -> 14678.016 | F40: =F39*(Summary!$I$24/12) -> 14788.101 | G40: =G39*(Summary!$I$24/12) -> 14899.011 | H40: =H39*(Summary!$I$24/12) -> 15010.754 | I40: =I39*(Summary!$I$24/12) -> 15123.335 | J40: =J39*(Summary!$I$24/12) -> 15236.76 | K40: =K39*(Summary!$I$24/12) -> 15351.035 | ... AM40: =AM39*(Summary!$I$24/12) -> 16793.21
B41: Interest Reserve Draw | D41: =MIN(MAX(0,D40-MAX(0,D30))) -> 14568.75 | E41: =MIN(MAX(0,E40-MAX(0,E30))) -> 14678.016 | F41: =MIN(MAX(0,F40-MAX(0,F30))) -> 14788.101 | G41: =MIN(MAX(0,G40-MAX(0,G30))) -> 14899.011 | H41: =MIN(MAX(0,H40-MAX(0,H30))) -> 15010.754 | I41: =MIN(MAX(0,I40-MAX(0,I30))) -> 15123.335 | J41: =MIN(MAX(0,J40-MAX(0,J30))) -> 15236.76 | K41: =MIN(MAX(0,K40-MAX(0,K30))) -> 12418.838 | ... AM41: =MIN(MAX(0,AM40-MAX(0,AM30))) -> 0
B43: Levered Cash Flow | C43: =-C37+IF(C30<0,0,MAX(0,C30-C40))+IF(C2=$A$9,-C39)+IF(C2=$A$9,-C28*Summary!$E$9) -> -974025 | D43: =-D37+IF(D30<0,0,MAX(0,D30-D40))+IF(D2=$A$9,-D39)+IF(D2=$A$9,-D28*Summary!$E$9) -> -42750.616 | E43: =-E37+IF(E30<0,0,MAX(0,E30-E40))+IF(E2=$A$9,-E39)+IF(E2=$A$9,-E28*Summary!$E$9) -> -42388.16 | F43: =-F37+IF(F30<0,0,MAX(0,F30-F40))+IF(F2=$A$9,-F39)+IF(F2=$A$9,-F28*Summary!$E$9) -> -55647.792 | G43: =-G37+IF(G30<0,0,MAX(0,G30-G40))+IF(G2=$A$9,-G39)+IF(G2=$A$9,-G28*Summary!$E$9) -> -54922.879 | H43: =-H37+IF(H30<0,0,MAX(0,H30-H40))+IF(H2=$A$9,-H39)+IF(H2=$A$9,-H28*Summary!$E$9) -> -54197.965 | I43: =-I37+IF(I30<0,0,MAX(0,I30-I40))+IF(I2=$A$9,-I39)+IF(I2=$A$9,-I28*Summary!$E$9) -> -53473.052 | J43: =-J37+IF(J30<0,0,MAX(0,J30-J40))+IF(J2=$A$9,-J39)+IF(J2=$A$9,-J28*Summary!$E$9) -> -11414.805 | ... AL43: =-AL37+IF(AL30<0,0,MAX(0,AL30-AL40))+IF(AL2=$A$9,-AL39)+IF(AL2=$A$9,-AL28*Summary!$E$9) -> 8822.496 | AM43: =-AM37+IF(AM30<0,0,MAX(0,AM30-AM40))+IF(AM2=$A$9,-AM39) -> 2494948.1
B44: IRR | C44: =XIRR(C43:AM43,C2:AM2) -> 0.25481161
B45: Equity Multiple | C45: =SUMIF(C43:AM43,">0")/-SUMIF(C43:AM43,"<0") -> 1.9152448
C48: Sensitivity Analysis
C50: Purchase Price | D50: IRR | E50: EMx | F50: Levered IRR | G50: Levered EMx | I50: Exit Cap Rate | J50: IRR | K50: EMx | L50: Levered IRR | M50: Levered EMx
D51: =C31 -> 0.17093083 | E51: =C32 -> 1.579728 | F51: =C44 -> 0.25481161 | G51: =C45 -> 1.9152448 | J51: =C31 -> 0.17093083 | K51: =C32 -> 1.579728 | L51: =C44 -> 0.25481161 | M51: =C45 -> 1.9152448
C52: 2000000 | D52: 0.29310825 | E52: 2.0966817 | F52: 0.76861075 | G52: 4.6694255 | I52: 0.05 | J52: 0.27289461 | K52: 2.0175761 | L52: 0.45912637 | M52: 2.962695
C53: 2250000 | D53: 0.24818802 | E53: 1.8964849 | F53: 0.51561282 | G53: 3.1897579 | I53: 0.055 | J53: 0.23472703 | K53: 1.8450905 | L53: 0.38552032 | M53: 2.5500631
C54: 2500000 | D54: 0.2089301 | E54: 1.7311866 | F54: 0.36642496 | G54: 2.4222006 | I54: 0.06 | J54: 0.20101433 | K54: 1.7013524 | L54: 0.31783636 | M54: 2.2062032
C55: 2775000 | D55: 0.17093083 | E55: 1.579728 | F55: 0.25481161 | G55: 1.9152448 | I55: 0.065 | J55: 0.17093083 | K55: 1.579728 | L55: 0.25481161 | M55: 1.9152448
C56: 3000000 | D56: 0.14313003 | E56: 1.4742025 | F56: 0.18625726 | G56: 1.6352258 | I56: 0.07 | J56: 0.14385296 | K56: 1.4754784 | L56: 0.19545889 | M56: 1.6658519
C57: 3250000 | D57: 0.11511553 | E57: 1.3723445 | F57: 0.12521217 | G57: 1.4067059 | I57: 0.075 | J57: 0.11929942 | K57: 1.3851288 | L57: 0.138978 | M57: 1.4497114
C58: 3500000 | D58: 0.089659306 | E58: 1.2836522 | F58: 0.075186571 | G58: 1.2342251 | I58: 0.08 | J58: 0.096891671 | K58: 1.3060728 | L58: 0.084694615 | M58: 1.2605885
C60: Renovated Rents | D60: IRR | E60: EMx | F60: Levered IRR | G60: Levered EMx | I60: Renovation Costs | J60: IRR | K60: EMx | L60: Levered IRR | M60: Levered EMx
D61: =C31 -> 0.17093083 | E61: =C32 -> 1.579728 | F61: =C44 -> 0.25481161 | G61: =C45 -> 1.9152448 | J61: =C31 -> 0.17093083 | K61: =C32 -> 1.579728 | L61: =C44 -> 0.25481161 | M61: =C45 -> 1.9152448
C62: 1100 | D62: -0.0046187967 | E62: 0.9866613 | F62: -0.21423489 | G62: 0.50587078 | I62: 0.4 | J62: 0.22360938 | K62: 1.7912975 | L62: 0.38644033 | M62: 2.6237152
C63: 1200 | D63: 0.070021847 | E63: 1.2167297 | F63: 0.016053286 | G63: 1.0463419 | I63: 0.6 | J63: 0.20538271 | K63: 1.7211075 | L63: 0.34100946 | M63: 2.3686178
C64: 1300 | D64: 0.13663856 | E64: 1.4493632 | F64: 0.17906237 | G64: 1.6008027 | I64: 0.8 | J64: 0.18783564 | K64: 1.6494924 | L64: 0.2967944 | M64: 2.1275289
C65: 1400 | D65: 0.1971841 | E65: 1.6846043 | F65: 0.31016198 | G65: 2.170183 | I65: 1 | J65: 0.17093083 | K65: 1.579728 | L65: 0.25481161 | M65: 1.9152448
C66: 1500 | D66: 0.25294651 | E66: 1.9223033 | F66: 0.42184765 | G66: 2.7542414 | I66: 1.2 | J66: 0.15463352 | K66: 1.5147135 | L66: 0.21581044 | M66: 1.7368799
C67: 1600 | D67: 0.30482553 | E67: 2.1617134 | F67: 0.52080911 | G67: 3.3487385 | I67: 1.4 | J67: 0.13891129 | K67: 1.4537543 | L67: 0.17936262 | M67: 1.5848103
C68: 1700 | D68: 0.35347732 | E68: 2.4023059 | F68: 0.61047997 | G68: 3.9510006 | I68: 1.6 | J68: 0.12373391 | K68: 1.3964097 | L68: 0.14531148 | M68: 1.4539432
C70: Unlevered IRR | D70: Avg Rents vs Renovation Costs | I70: Unlevered IRR | J70: Renovated Rents vs Exit Cap
C71: =C31 -> 0.17093083 | D71: 1200 | E71: 1400 | F71: 1600 | G71: 1800 | I71: =C31 -> 0.17093083 | J71: 0.055 | K71: 0.06 | L71: 0.065 | M71: 0.07
C72: 0.4 | D72: 0.1208224 | E72: 0.25035929 | F72: 0.36006969 | G72: 0.45650063 | I72: 1100 | J72: 0.050682434 | K72: 0.021463504 | L72: -0.0046187967 | M72: -0.028102961
C73: 0.6 | D73: 0.10322122 | E73: 0.23196673 | F73: 0.34098433 | G73: 0.43679069 | I73: 1200 | J73: 0.12895719 | K73: 0.097815949 | L73: 0.070021847 | M73: 0.045000055
C74: 0.8 | D74: 0.086300531 | E74: 0.21425403 | F74: 0.32258168 | G74: 0.41776802 | I74: 1300 | J74: 0.19878985 | K74: 0.16594737 | L74: 0.13663856 | M74: 0.11025639
C75: 1 | D75: 0.070021847 | E75: 0.1971841 | F75: 0.30482553 | G75: 0.39939695 | I75: 1400 | J75: 0.26223465 | K75: 0.22785835 | L75: 0.1971841 | M75: 0.16957578
C76: 1.2 | D76: 0.054349366 | E76: 0.18072241 | F76: 0.28768205 | G76: 0.38164414 | I76: 1500 | J76: 0.3206467 | K76: 0.28486854 | L76: 0.25294651 | M76: 0.22421786
C77: 1.4 | D77: 0.039249763 | E77: 0.16483672 | F77: 0.27111966 | G77: 0.36447838 | I77: 1600 | J77: 0.37497258 | K77: 0.33789976 | L77: 0.30482553 | M77: 0.27506246
C78: 1.6 | D78: 0.024692014 | E78: 0.14949697 | F78: 0.25510885 | G78: 0.3478705 | I78: 1700 | J78: 0.42590272 | K78: 0.38762434 | L78: 0.35347732 | M78: 0.32275129

Sheet Yearly Roll Up
A2: Cash Flow Projections | C2: Year 0 | D2: Year 1 | E2: Year 2 | F2: Year 3
A4: Analysis Start Date | B4: Units renovated by month | D4: =SUMIFS('Monthly DCF'!$D4:$AM4,'Monthly DCF'!$D$3:$AM$3,">=1",'Monthly DCF'!$D$3:$AM$3,"<=12") -> 20 | E4: =SUMIFS('Monthly DCF'!$D$4:$AM$4,'Monthly DCF'!$D$3:$AM$3,">=13",'Monthly DCF'!$D$3:$AM$3,"<=24") -> 17 | F4: =SUMIFS('Monthly DCF'!$D$4:$AM$4,'Monthly DCF'!$D$3:$AM$3,">=25",'Monthly DCF'!$D$3:$AM$3,"<=36") -> 0
A5: 46388 | B5: Cumulative Renovated Units | D5: =D4+SUM($C$4:C4) -> 20 | E5: =E4+SUM($C$4:D4) -> 37 | F5: =F4+SUM($C$4:E4) -> 37
A6: Renovation Timeline (Months) | B6: Renovated Units Online | D6: =D5 -> 20 | E6: =E5 -> 37 | F6: =F5 -> 37
A7: 24 | B7: Unrenovated Units Online | D7: =37-D6 -> 17 | E7: =37-E6 -> 0 | F7: =37-F6 -> 0
A8: Sale Date
A9: 47484
B10: Gross Rental Income | D10: =SUMIFS('Monthly DCF'!$D10:$AM10,'Monthly DCF'!$D$3:$AM$3,">=1",'Monthly DCF'!$D$3:$AM$3,"<=12") -> 377962.25 | E10: =SUMIFS('Monthly DCF'!$D10:$AM10,'Monthly DCF'!$D$3:$AM$3,">=13",'Monthly DCF'!$D$3:$AM$3,"<=24") -> 525768.23 | F10: =SUMIFS('Monthly DCF'!$D10:$AM10,'Monthly DCF'!$D$3:$AM$3,">=25",'Monthly DCF'!$D$3:$AM$3,"<=36") -> 601866.67
B11: Other Income | D11: =SUMIFS('Monthly DCF'!$D11:$AM11,'Monthly DCF'!$D$3:$AM$3,">=1",'Monthly DCF'!$D$3:$AM$3,"<=12") -> 11500 | E11: =SUMIFS('Monthly DCF'!$D11:$AM11,'Monthly DCF'!$D$3:$AM$3,">=13",'Monthly DCF'!$D$3:$AM$3,"<=24") -> 11500 | F11: =SUMIFS('Monthly DCF'!$D11:$AM11,'Monthly DCF'!$D$3:$AM$3,">=25",'Monthly DCF'!$D$3:$AM$3,"<=36") -> 11500
B12: Stabilized Vacancy | D12: =SUMIFS('Monthly DCF'!$D12:$AM12,'Monthly DCF'!$D$3:$AM$3,">=1",'Monthly DCF'!$D$3:$AM$3,"<=12") -> -27015.265 | E12: =SUMIFS('Monthly DCF'!$D12:$AM12,'Monthly DCF'!$D$3:$AM$3,">=13",'Monthly DCF'!$D$3:$AM$3,"<=24") -> -30195.136 | F12: =SUMIFS('Monthly DCF'!$D12:$AM12,'Monthly DCF'!$D$3:$AM$3,">=25",'Monthly DCF'!$D$3:$AM$3,"<=36") -> -32533.333
B13: Concessions/Bad Debt | D13: =SUMIFS('Monthly DCF'!$D13:$AM13,'Monthly DCF'!$D$3:$AM$3,">=1",'Monthly DCF'!$D$3:$AM$3,"<=12") -> -8982.5784 | E13: =SUMIFS('Monthly DCF'!$D13:$AM13,'Monthly DCF'!$D$3:$AM$3,">=13",'Monthly DCF'!$D$3:$AM$3,"<=24") -> -15137.809 | F13: =SUMIFS('Monthly DCF'!$D13:$AM13,'Monthly DCF'!$D$3:$AM$3,">=25",'Monthly DCF'!$D$3:$AM$3,"<=36") -> -18056
B14: Effective Gross Income | D14: =SUMIFS('Monthly DCF'!$D14:$AM14,'Monthly DCF'!$D$3:$AM$3,">=1",'Monthly DCF'!$D$3:$AM$3,"<=12") -> 353464.41 | E14: =SUMIFS('Monthly DCF'!$D14:$AM14,'Monthly DCF'!$D$3:$AM$3,">=13",'Monthly DCF'!$D$3:$AM$3,"<=24") -> 491935.28 | F14: =SUMIFS('Monthly DCF'!$D14:$AM14,'Monthly DCF'!$D$3:$AM$3,">=25",'Monthly DCF'!$D$3:$AM$3,"<=36") -> 562777.33
B16: Operating Expenses | D16: =SUMIFS('Monthly DCF'!$D16:$AM16,'Monthly DCF'!$D$3:$AM$3,">=1",'Monthly DCF'!$D$3:$AM$3,"<=12") -> -166194.62 | E16: =SUMIFS('Monthly DCF'!$D16:$AM16,'Monthly DCF'!$D$3:$AM$3,">=13",'Monthly DCF'!$D$3:$AM$3,"<=24") -> -218151.32 | F16: =SUMIFS('Monthly DCF'!$D16:$AM16,'Monthly DCF'!$D$3:$AM$3,">=25",'Monthly DCF'!$D$3:$AM$3,"<=36") -> -246138.87
B18: Net Operating Income | D18: =SUMIFS('Monthly DCF'!$D18:$AM18,'Monthly DCF'!$D$3:$AM$3,">=1",'Monthly DCF'!$D$3:$AM$3,"<=12") -> 187269.79 | E18: =SUMIFS('Monthly DCF'!$D18:$AM18,'Monthly DCF'!$D$3:$AM$3,">=13",'Monthly DCF'!$D$3:$AM$3,"<=24") -> 273783.96 | F18: =SUMIFS('Monthly DCF'!$D18:$AM18,'Monthly DCF'!$D$3:$AM$3,">=25",'Monthly DCF'!$D$3:$AM$3,"<=36") -> 316638.47
B19: Capex | D19: =SUMIFS('Monthly DCF'!$D19:$AM19,'Monthly DCF'!$D$3:$AM$3,">=1",'Monthly DCF'!$D$3:$AM$3,"<=12") -> -9250 | E19: =SUMIFS('Monthly DCF'!$D19:$AM19,'Monthly DCF'!$D$3:$AM$3,">=13",'Monthly DCF'!$D$3:$AM$3,"<=24") -> -9250 | F19: =SUMIFS('Monthly DCF'!$D19:$AM19,'Monthly DCF'!$D$3:$AM$3,">=25",'Monthly DCF'!$D$3:$AM$3,"<=36") -> -9250
B20: Free Cash Flow | D20: =SUMIFS('Monthly DCF'!$D20:$AM20,'Monthly DCF'!$D$3:$AM$3,">=1",'Monthly DCF'!$D$3:$AM$3,"<=12") -> 178019.79 | E20: =SUMIFS('Monthly DCF'!$D20:$AM20,'Monthly DCF'!$D$3:$AM$3,">=13",'Monthly DCF'!$D$3:$AM$3,"<=24") -> 264533.96 | F20: =SUMIFS('Monthly DCF'!$D20:$AM20,'Monthly DCF'!$D$3:$AM$3,">=25",'Monthly DCF'!$D$3:$AM$3,"<=36") -> 307388.47
B22: Purchase Price + Closing Costs | C22: ='Monthly DCF'!C22 -> -2858250
B24: Renovations
B25: Interior Renovations | D25: =SUMIFS('Monthly DCF'!$D25:$AM25,'Monthly DCF'!$D$3:$AM$3,">=1",'Monthly DCF'!$D$3:$AM$3,"<=12") -> -265945.95 | E25: =SUMIFS('Monthly DCF'!$D25:$AM25,'Monthly DCF'!$D$3:$AM$3,">=13",'Monthly DCF'!$D$3:$AM$3,"<=24") -> -226054.05
B26: Exterior Renovations | D26: =SUMIFS('Monthly DCF'!$D26:$AM26,'Monthly DCF'!$D$3:$AM$3,">=1",'Monthly DCF'!$D$3:$AM$3,"<=12") -> -248000
B28: Reversion Value | F28: =SUMIFS('Monthly DCF'!$D28:$AM28,'Monthly DCF'!$D$3:$AM$3,">=25",'Monthly DCF'!$D$3:$AM$3,"<=36") -> 4725220.2
B30: Unlevered Cash Flow | C30: ='Monthly DCF'!C30 -> -2858250 | D30: =SUMIFS('Monthly DCF'!$D30:$AM30,'Monthly DCF'!$D$3:$AM$3,">=1",'Monthly DCF'!$D$3:$AM$3,"<=12") -> -335926.15 | E30: =SUMIFS('Monthly DCF'!$D30:$AM30,'Monthly DCF'!$D$3:$AM$3,">=13",'Monthly DCF'!$D$3:$AM$3,"<=24") -> 38479.904 | F30: =SUMIFS('Monthly DCF'!$D30:$AM30,'Monthly DCF'!$D$3:$AM$3,">=25",'Monthly DCF'!$D$3:$AM$3,"<=36") -> 5032608.7
B31: IRR | C31: ='Monthly DCF'!C31 -> 0.17093083
B32: Equity Multiple | C32: ='Monthly DCF'!C32 -> 1.579728
B34: Amount
A35: Senior Loan | B35: =Summary!E22 -> 1942500 | C35: ='Monthly DCF'!C35 -> 1942500 | D35: =SUMIFS('Monthly DCF'!$D35:$AM35,'Monthly DCF'!$D$3:$AM$3,">=1",'Monthly DCF'!$D$3:$AM$3,"<=12") -> 0 | E35: =SUMIFS('Monthly DCF'!$D35:$AM35,'Monthly DCF'!$D$3:$AM$3,">=13",'Monthly DCF'!$D$3:$AM$3,"<=24") -> 0 | F35: =SUMIFS('Monthly DCF'!$D35:$AM35,'Monthly DCF'!$D$3:$AM$3,">=25",'Monthly DCF'!$D$3:$AM$3,"<=36") -> 0
A36: Loan Closing Costs | B36: =Summary!E22*0.03 -> 58275 | C36: ='Monthly DCF'!C36 -> 0 | D36: =SUMIFS('Monthly DCF'!$D36:$AM36,'Monthly DCF'!$D$3:$AM$3,">=1",'Monthly DCF'!$D$3:$AM$3,"<=12") -> 0 | E36: =SUMIFS('Monthly DCF'!$D36:$AM36,'Monthly DCF'!$D$3:$AM$3,">=13",'Monthly DCF'!$D$3:$AM$3,"<=24") -> 0 | F36: =SUMIFS('Monthly DCF'!$D36:$AM36,'Monthly DCF'!$D$3:$AM$3,">=25",'Monthly DCF'!$D$3:$AM$3,"<=36") -> 0
A37: Equity Draw | B37: =SUM(C37:AN37) -> 1353349.5 | C37: ='Monthly DCF'!C37 -> 974025 | D37: =SUMIFS('Monthly DCF'!$D37:$AM37,'Monthly DCF'!$D$3:$AM$3,">=1",'Monthly DCF'!$D$3:$AM$3,"<=12") -> 342877.92 | E37: =SUMIFS('Monthly DCF'!$D37:$AM37,'Monthly DCF'!$D$3:$AM$3,">=13",'Monthly DCF'!$D$3:$AM$3,"<=24") -> 36446.535 | F37: =SUMIFS('Monthly DCF'!$D37:$AM37,'Monthly DCF'!$D$3:$AM$3,">=25",'Monthly DCF'!$D$3:$AM$3,"<=36") -> 0
A39: Financing Cost | B39: Loan Balance | C39: ='Monthly DCF'!C39 -> 1942500 | D39: ='Monthly DCF'!O39 -> 2101854.7 | E39: ='Monthly DCF'!AA39 -> 2233971 | F39: ='Monthly DCF'!AM39 -> 2239094.6
B40: Interest Expense | C40: ='Monthly DCF'!C40 -> 0 | D40: =SUMIFS('Monthly DCF'!$D40:$AM40,'Monthly DCF'!$D$3:$AM$3,">=1",'Monthly DCF'!$D$3:$AM$3,"<=12") -> 182070.42 | E40: =SUMIFS('Monthly DCF'!$D40:$AM40,'Monthly DCF'!$D$3:$AM$3,">=13",'Monthly DCF'!$D$3:$AM$3,"<=24") -> 196402.39 | F40: =SUMIFS('Monthly DCF'!$D40:$AM40,'Monthly DCF'!$D$3:$AM$3,">=25",'Monthly DCF'!$D$3:$AM$3,"<=36") -> 201518.51
B41: Interest Reserve Draw | C41: ='Monthly DCF'!C41 -> 0 | D41: =SUMIFS('Monthly DCF'!$D41:$AM41,'Monthly DCF'!$D$3:$AM$3,">=1",'Monthly DCF'!$D$3:$AM$3,"<=12") -> 175118.65 | E41: =SUMIFS('Monthly DCF'!$D41:$AM41,'Monthly DCF'!$D$3:$AM$3,">=13",'Monthly DCF'!$D$3:$AM$3,"<=24") -> 121475.95 | F41: =SUMIFS('Monthly DCF'!$D41:$AM41,'Monthly DCF'!$D$3:$AM$3,">=25",'Monthly DCF'!$D$3:$AM$3,"<=36") -> 0
B43: Levered Cash Flow | C43: ='Monthly DCF'!C43 -> -974025 | D43: =SUMIFS('Monthly DCF'!$D43:$AM43,'Monthly DCF'!$D$3:$AM$3,">=1",'Monthly DCF'!$D$3:$AM$3,"<=12") -> -342877.92 | E43: =SUMIFS('Monthly DCF'!$D43:$AM43,'Monthly DCF'!$D$3:$AM$3,">=13",'Monthly DCF'!$D$3:$AM$3,"<=24") -> -36446.535 | F43: =SUMIFS('Monthly DCF'!$D43:$AM43,'Monthly DCF'!$D$3:$AM$3,">=25",'Monthly DCF'!$D$3:$AM$3,"<=36") -> 2591995.5
B44: IRR | C44: ='Monthly DCF'!C44 -> 0.25481161
B45: Equity Multiple | C45: ='Monthly DCF'!C45 -> 1.9152448

Sheet Sale Comps
B2: Acquisition Comps | G2: Exit Sale Comps
B3: Address | C3: 4200 N 27th St | D3: SF | E3: 22100 | G3: Address | H3: 4231-4237 N 27th St | I3: SF | J3: 16150
B4: Submarket | C4: Biltmore | D4: Sale Price | E4: 4750000 | G4: Submarket | H4: Biltmore | I4: Sale Price | J4: 4700000
B5: Sale Date | C5: June 2026 | D5: Price/Unit | E5: =E4/C7 -> 237500 | G5: Sale Date | H5: November 2025 | I5: Price/Unit | J5: =J4/H7 -> 235000
B6: Year Built | C6: 1962 | D6: Price/SF | E6: =E4/E3 -> 214.93213 | G6: Year Built | H6: 1970/2017 | I6: Price/SF | J6: =J4/J3 -> 291.02167
B7: No. Units | C7: 20 | D7: Cap Rate | E7: 0.05 | G7: No. Units | H7: 20 | I7: Cap Rate
B8: Address | C8: 4917 E Holly St | D8: SF | E8: 19328 | G8: Address | H8: 2402 W Devonshire | I8: SF | J8: 29610
B9: Submarket | C9: Papago | D9: Sale Price | E9: 4110000 | G9: Submarket | H9: Midtown | I9: Sale Price | J9: 6030000
B10: Sale Date | C10: July 2025 | D10: Price/Unit | E10: =E9/C12 -> 186818.18 | G10: Sale Date | H10: December 2025 | I10: Price/Unit | J10: =J9/H12 -> 182727.27
B11: Year Built | C11: 1963 | D11: Price/SF | E11: =E9/E8 -> 212.64487 | G11: Year Built | H11: 1963/2019 | I11: Price/SF | J11: =J9/J8 -> 203.64742
B12: No. Units | C12: 22 | D12: Cap Rate | G12: No. Units | H12: 33 | I12: Cap Rate | J12: 0.061
B13: Address | C13: 7325 E Belleview St | D13: SF | E13: 15740 | G13: Address | H13: 31 W 2nd St | I13: SF | J13: 15672
B14: Submarket | C14: South Scottsdale | D14: Sale Price | E14: 5620000 | G14: Submarket | H14: Downtown Mesa | I14: Sale Price | J14: 3450000
B15: Sale Date | C15: July 2026 | D15: Price/Unit | E15: =E14/C17 -> 281000 | G15: Sale Date | H15: January 2026 | I15: Price/Unit | J15: =J14/H17 -> 172500
B16: Year Built | C16: 1969 | D16: Price/SF | E16: =E14/E13 -> 357.0521 | G16: Year Built | H16: 1960/2015 | I16: Price/SF | J16: =J14/J13 -> 220.13783
B17: No. Units | C17: 20 | D17: Cap Rate | E17: 0.0575 | G17: No. Units | H17: 20 | I17: Cap Rate | J17: 0.059
B18: Address | C18: 25 E Eva St | D18: SF | E18: 15328 | G18: Address | H18: 3710 E McDowell Rd | I18: SF | J18: 27815
B19: Submarket | C19: North Mountain | D19: Sale Price | E19: 2830000 | G19: Submarket | H19: Papago | I19: Sale Price | J19: 6630000
B20: Sale Date | C20: March 2026 | D20: Price/Unit | E20: =E19/C22 -> 128636.36 | G20: Sale Date | H20: January 2026 | I20: Price/Unit | J20: =J19/H22 -> 132600
B21: Year Built | C21: 1960 | D21: Price/SF | E21: =E19/E18 -> 184.62944 | G21: Year Built | H21: 1979/2020 | I21: Price/SF | J21: =J19/J18 -> 238.3606
B22: No. Units | C22: 22 | D22: Cap Rate | G22: No. Units | H22: 50 | I22: Cap Rate | J22: 0.065
B23: Address | C23: 6730 N 17th Ave | D23: SF | E23: 17030 | G23: Address | H23: 2101 W Colter St | I23: SF | J23: 30673
B24: Submarket | C24: North Phoenix | D24: Sale Price | E24: 3530000 | G24: Submarket | H24: Midtown | I24: Sale Price | J24: 4750000
B25: Sale Date | C25: October 2025 | D25: Price/Unit | E25: =E24/C27 -> 168095.24 | G25: Sale Date | H25: July 2025 | I25: Price/Unit | J25: =J24/H27 -> 182692.31
B26: Year Built | C26: 1969 | D26: Price/SF | E26: =E24/E23 -> 207.28127 | G26: Year Built | H26: 1983/2018 | I26: Price/SF | J26: =J24/J23 -> 154.85932
B27: No. Units | C27: 21 | D27: Cap Rate | G27: No. Units | H27: 26 | I27: Cap Rate | J27: 0.05
B28: Address | C28: 5407 W Glenrosa Ave | D28: SF | E28: 33840 | G28: Address | H28: 2339 W Northern Ave | I28: SF | J28: 43174
B29: Submarket | C29: Maryvale | D29: Sale Price | E29: 4500000 | G29: Submarket | H29: North Phoenix | I29: Sale Price | J29: 8860000
B30: Sale Date | C30: October 2025 | D30: Price/Unit | E30: =E29/C32 -> 125000 | G30: Sale Date | H30: May 2025 | I30: Price/Unit | J30: =J29/H32 -> 173725.49
B31: Year Built | C31: 1963 | D31: Price/SF | E31: =E29/E28 -> 132.97872 | G31: Year Built | H31: 1964/2021 | I31: Price/SF | J31: =J29/J28 -> 205.2161
B32: No. Units | C32: 36 | D32: Cap Rate | E32: 0.054 | G32: No. Units | H32: 51 | I32: Cap Rate | J32: 0.055
B33: Address | C33: 1806 E Concorda Dr | D33: SF | E33: 46376 | G33: Address | H33: 3025 N 32nd St | I33: SF | J33: 28741
B34: Submarket | C34: Alameda | D34: Sale Price | E34: 7400000 | G34: Submarket | H34: East Phoenix | I34: Sale Price | J34: 8250000
B35: Sale Date | C35: January 2026 | D35: Price/Unit | E35: =E34/C37 -> 168181.82 | G35: Sale Date | H35: May 2025 | I35: Price/Unit | J35: =J34/H37 -> 133064.52
B36: Year Built | C36: 1963 | D36: Price/SF | E36: =E34/E33 -> 159.56529 | G36: Year Built | H36: 1968/2015 | I36: Price/SF | J36: =J34/J33 -> 287.04638
B37: No. Units | C37: 44 | D37: Cap Rate | G37: No. Units | H37: 62 | I37: Cap Rate | J37: 0.061
B38: Address | C38: 2011 N 51st St | D38: SF | E38: 14960 | G38: Address | H38: 6315 N 16th St | I38: SF | J38: 72326
B39: Submarket | C39: Papago | D39: Sale Price | E39: 4750000 | G39: Submarket | H39: North Phoenix | I39: Sale Price | J39: 19500000
B40: Sale Date | C40: June 2026 | D40: Price/Unit | E40: =E39/C42 -> 237500 | G40: Sale Date | H40: March 2026 | I40: Price/Unit | J40: =J39/H42 -> 226744.19
B41: Year Built | C41: 1979 | D41: Price/SF | E41: =E39/E38 -> 317.51337 | G41: Year Built | H41: 1969/2024 | I41: Price/SF | J41: =J39/J38 -> 269.61259
B42: No. Units | C42: 20 | D42: Cap Rate | E42: 0.079 | G42: No. Units | H42: 86 | I42: Cap Rate
B43: Address | C43: 302 E Monte Vista | D43: SF | E43: 33800 | G43: Implied Property Value | I43: Summary
B44: Submarket | C44: Encanto | D44: Sale Price | E44: 11500000 | G44: Med Price/Unit | H44: =J44*Summary!$C$7 -> 6593729.3 | I44: Med Price/Unit | J44: =MEDIAN(J5,J10,J15,J20,J25,J30,J35,J40) -> 178208.9
B45: Sale Date | C45: March 2026 | D45: Price/Unit | E45: =E44/C47 -> 191666.67 | G45: Avg Price/Unit | H45: =J45*Summary!$C$7 -> 6655623.7 | I45: Avg Price/Unit | J45: =AVERAGE(J5,J10,J15,J20,J25,J30,J35,J40) -> 179881.72
B46: Year Built | C46: 1972 | D46: Price/SF | E46: =E44/E43 -> 340.23669 | G46: Med Price/SF | H46: =J46*Summary!$C$8 -> 8858189.5 | I46: Med Price/SF | J46: =MEDIAN(J6,J11,J16,J21,J26,J31,J36,J41) -> 229.24921
B47: No. Units | C47: 60 | D47: Cap Rate | E47: 0.067 | G47: Avg Price/SF | H47: =J47*Summary!$C$8 -> 9031626.2 | I47: Avg Price/SF | J47: =AVERAGE(J6,J11,J16,J21,J26,J31,J36,J41) -> 233.73774
B48: Address | C48: 1820-1860 E Hayden Ln | D48: SF | E48: 47356 | G48: Med Cap Rate | H48: ='Income Statements'!I24/'Sale Comps'!J48 -> 5277307.8 | I48: Med Cap Rate | J48: =MEDIAN(J12,J17,J22,J27,J32,J37) -> 0.06
B49: Submarket | C49: Apache | D49: Sale Price | E49: 10400000 | G49: Avg Cap Rate | H49: ='Income Statements'!I24/'Sale Comps'!J49 -> 5412623.4 | I49: Avg Cap Rate | J49: =AVERAGE(J12,J17,J22,J27,J32,J37) -> 0.0585
B50: Sale Date | C50: November 2025 | D50: Price/Unit | E50: =E49/C52 -> 185714.29
B51: Year Built | C51: 1981 | D51: Price/SF | E51: =E49/E48 -> 219.61314
B52: No. Units | C52: 56 | D52: Cap Rate
B53: Implied Property Value | D53: Summary
B54: Med Price/Unit | C54: =E54*Summary!$C$7 -> 6891850.6 | D54: Median Price/Unit | E54: =MEDIAN(E5,E10,E15,E20,E25,E30,E35,E40,E45,E50) -> 186266.23
B55: Avg Price/Unit | C55: =E55*Summary!$C$7 -> 7067416.5 | D55: Avg Price/Unit | E55: =AVERAGE(E5,E10,E15,E20,E25,E30,E35,E40,E45,E50) -> 191011.26
B56: Med Price/SF | C56: =E56*Summary!$C$8 -> 8260787.5 | D56: Median Price/SF | E56: =MEDIAN(E6,E11,E16,E21,E26,E31,E36,E41,E46,E51) -> 213.7885
B57: Avg Price/SF | C57: =E57*Summary!$C$8 -> 9066671.2 | D57: Avg Price/SF | E57: =AVERAGE(E6,E11,E16,E21,E26,E31,E36,E41,E46,E51) -> 234.6447
B58: Med Cap Rate | C58: ='Income Statements'!C24/'Sale Comps'!E58 -> 2707959.6 | D58: Median Cap Rate | E58: =MEDIAN(E7,E17,E32,E42,E47) -> 0.0575
B59: Avg Cap Rate | C59: ='Income Statements'!C24/'Sale Comps'!E59 -> 2531832.1 | D59: Avg. Cap Rate | E59: =AVERAGE(E47,E42,E32,E17,E7) -> 0.0615

Sheet Rent Comps
B2: Rent Comps-Post Renovation
B3: Address | C3: 6315 N 16th St | D3: 1 Bed | F3: 1 Bed SF | H3: $/SF
B4: Submarket | C4: North Phoenix | D4: 2 Bed | E4: 1833 | F4: 2 Bed SF | G4: 841 | H4: $/SF | I4: =E4/G4 -> 2.1795482
B5: Year Built | C5: 1969/2024 | D5: 3 Bed | E5: 2089 | F5: 3 Bed SF | G5: 1026 | H5: $/SF | I5: =E5/G5 -> 2.0360624
B6: Class | C6: B | D6: Avg. | E6: =AVERAGE(E4:E5) -> 1961 | F6: Avg. SF | G6: =AVERAGE(G4:G5) -> 933.5 | H6: $/SF | I6: =E6/G6 -> 2.1006963
B7: Address | C7: 6201 N 16th St | D7: 1 Bed | E7: 965 | F7: 1 Bed SF | G7: 672 | H7: $/SF | I7: =E7/G7 -> 1.4360119
B8: Submarket | C8: North Phoenix | D8: 2 Bed | E8: 1115 | F8: 2 Bed SF | G8: 952 | H8: $/SF | I8: =E8/G8 -> 1.1712185
B9: Year Built | C9: 1971/2022 | D9: 3 Bed | F9: 3 Bed SF | H9: $/SF
B10: Class | C10: C | D10: Avg. | E10: =AVERAGE(E7:E9) -> 1040 | F10: Avg. SF | G10: =AVERAGE(G7:G9) -> 812 | H10: $/SF | I10: =E10/G10 -> 1.2807882
B11: Address | C11: 6702 N 17th Ave | D11: 1 Bed | E11: 768 | F11: 1 Bed SF | G11: 600 | H11: $/SF | I11: =E11/G11 -> 1.28
B12: Submarket | C12: North Phoenix | D12: 2 Bed | E12: 995 | F12: 2 Bed SF | G12: 875 | H12: $/SF | I12: =E12/G12 -> 1.1371429
B13: Year Built | C13: 1979/2022 | D13: 3 Bed | F13: 3 Bed SF | H13: $/SF
B14: Class | C14: C | D14: Avg. | E14: =AVERAGE(E11:E13) -> 881.5 | F14: Avg. SF | G14: =AVERAGE(G11:G13) -> 737.5 | H14: $/SF | I14: =E14/G14 -> 1.1952542
B15: Address | C15: 4811-4815 N 15th Ave | D15: 1 Bed | E15: 799 | F15: 1 Bed SF | G15: 512 | H15: $/SF | I15: =E15/G15 -> 1.5605469
B16: Submarket | C16: Midtown | D16: 2 Bed | E16: 1090 | F16: 2 Bed SF | G16: 887 | H16: $/SF | I16: =E16/G16 -> 1.2288613
B17: Year Built | C17: 1958/2023 | D17: 3 Bed | F17: 3 Bed SF | H17: $/SF
B18: Class | C18: C | D18: Avg. | E18: =AVERAGE(E15:E17) -> 944.5 | F18: Avg. SF | G18: =AVERAGE(G15:G17) -> 699.5 | H18: $/SF | I18: =E18/G18 -> 1.3502502
B19: Address | C19: 4150 N 25th St | D19: 1 Bed | E19: 1466 | F19: 1 Bed SF | G19: 510 | H19: $/SF | I19: =E19/G19 -> 2.8745098
B20: Submarket | C20: Biltmore | D20: 2 Bed | E20: 1857 | F20: 2 Bed SF | G20: 725 | H20: $/SF | I20: =E20/G20 -> 2.5613793
B21: Year Built | C21: 1957/2021 | D21: 3 Bed | F21: 3 Bed SF | H21: $/SF
B22: Class | C22: C | D22: Avg. | E22: =AVERAGE(E19:E21) -> 1661.5 | F22: Avg. SF | G22: =AVERAGE(G19:G21) -> 617.5 | H22: $/SF | I22: =E22/G22 -> 2.6906883
B23: Address | C23: 2242-2302 E Pinchot Ave | D23: 1 Bed | E23: 1227 | F23: 1 Bed SF | G23: 755 | H23: $/SF | I23: =E23/G23 -> 1.6251656
B24: Submarket | C24: Biltmore | D24: 2 Bed | E24: 1054 | F24: 2 Bed SF | G24: 813 | H24: $/SF | I24: =E24/G24 -> 1.296433
B25: Year Built | C25: 1967/2021 | D25: 3 Bed | E25: 1397 | F25: 3 Bed SF | G25: 1058 | H25: $/SF | I25: =E25/G25 -> 1.3204159
B26: Class | C26: C | D26: Avg. | E26: =AVERAGE(E23:E25) -> 1226 | F26: Avg. SF | G26: =AVERAGE(G23:G25) -> 875.33333 | H26: $/SF | I26: =E26/G26 -> 1.4006093
B27: Address | C27: 2512 E Thomas Rd | D27: 1 Bed | E27: 1339 | F27: 1 Bed SF | G27: 600 | H27: $/SF | I27: =E27/G27 -> 2.2316667
B28: Submarket | C28: Biltmore | D28: 2 Bed | E28: 1521 | F28: 2 Bed SF | G28: 810 | H28: $/SF | I28: =E28/G28 -> 1.8777778
B29: Year Built | C29: 1945/2021 | D29: 3 Bed | F29: 3 Bed SF | H29: $/SF
B30: Class | C30: B | D30: Avg. | E30: =AVERAGE(E27:E29) -> 1430 | F30: Avg. SF | G30: =AVERAGE(G27:G29) -> 705 | H30: $/SF | I30: =E30/G30 -> 2.0283688
B31: Address | C31: 6725 E Earll Dr | D31: 1 Bed | E31: 1425 | F31: 1 Bed SF | G31: 550 | H31: $/SF | I31: =E31/G31 -> 2.5909091
B32: Submarket | C32: Old Town | D32: 2 Bed | E32: 1611 | F32: 2 Bed SF | G32: 769 | H32: $/SF | I32: =E32/G32 -> 2.0949285
B33: Year Built | C33: 1958/2023 | D33: 3 Bed | F33: 3 Bed SF | H33: $/SF
B34: Class | C34: C | D34: Avg. | E34: =AVERAGE(E31:E33) -> 1518 | F34: Avg. SF | G34: =AVERAGE(G31:G33) -> 659.5 | H34: $/SF | I34: =E34/G34 -> 2.3017437
B35: Address | C35: 7102 E Oak St | D35: 1 Bed | E35: 1420 | F35: 1 Bed SF | G35: 650 | H35: $/SF | I35: =E35/G35 -> 2.1846154
B36: Submarket | C36: South Scottsdale | D36: 2 Bed | E36: 1650 | F36: 2 Bed SF | G36: 800 | H36: $/SF | I36: =E36/G36 -> 2.0625
B37: Year Built | C37: 1960/2020 | D37: 3 Bed | F37: 3 Bed SF | H37: $/SF
B38: Class | C38: C | D38: Avg. | E38: =AVERAGE(E35:E37) -> 1535 | F38: Avg. SF | G38: =AVERAGE(G35:G37) -> 725 | H38: $/SF | I38: =E38/G38 -> 2.1172414
B39: Address | C39: 2019-2025 E Turney Ave | D39: 1 Bed | E39: 1053 | F39: 1 Bed SF | G39: 624 | H39: $/SF | I39: =E39/G39 -> 1.6875
B40: Submarket | C40: Biltmore | D40: 2 Bed | E40: 1319 | F40: 2 Bed SF | G40: 729 | H40: $/SF | I40: =E40/G40 -> 1.8093278
B41: Year Built | C41: 1960 | D41: 3 Bed | E41: 2005 | F41: 3 Bed SF | G41: 950 | H41: $/SF | I41: =E41/G41 -> 2.1105263
B42: Class | C42: B | D42: Avg. | E42: =AVERAGE(E39:E41) -> 1459 | F42: Avg. SF | G42: =AVERAGE(G39:G41) -> 767.66667 | H42: $/SF | I42: =E42/G42 -> 1.9005645
D43: Avg. 1 Bed | E43: =AVERAGE((E39,E35,E31,E27,E23,E19,E15,E11,E7,E3)) -> 1162.4444 | H43: Avg. 1 Bed | I43: =AVERAGE((I39,I35,I31,I27,I23,I19,I15,I11,I7,I3)) -> 1.9412139
D44: Avg. 2 Bed | E44: =AVERAGE((E40,E36,E32,E28,E24,E20,E16,E12,E8,E4)) -> 1404.5 | H44: Avg. 2 Bed | I44: =AVERAGE((I40,I36,I32,I28,I24,I20,I16,I12,I8,I4)) -> 1.7419117
D45: Avg. 3 Bed | E45: =AVERAGE((E41,E37,E33,E29,E25,E21,E17,E13,E9,E5)) -> 1830.3333 | H45: Avg. 3 Bed | I45: =AVERAGE((I41,I37,I33,I29,I25,I21,I17,I13,I9,I5)) -> 1.8223349
D46: Avg. Total | E46: =AVERAGE((E42,E38,E34,E30,E26,E22,E18,E14,E10,E6)) -> 1365.65 | H46: Avg. Total | I46: =AVERAGE((I42,I38,I34,I30,I26,I22,I18,I14,I10,I6)) -> 1.8366205
